LICENSE
MANIFEST.in
README.rst
setup.py
docs/README.rst
src/unix_daemon.py
src/unix_daemon.egg-info/PKG-INFO
src/unix_daemon.egg-info/SOURCES.txt
src/unix_daemon.egg-info/dependency_links.txt
src/unix_daemon.egg-info/top_level.txt