Metadata-Version: 1.1
Name: unix-daemon
Version: 0.1.4
Summary: Function emulating Daemon(3) on Linux and Unix OS.
Home-page: https://github.com/wbcchsyn/unix_daemon
Author: Yoshida Shin
Author-email: wbcchsyn@gmail.com
License: ['Apache License 2.0']
Platform: linux
Platform: unix
Classifier: Development Status :: 4 - Beta
Classifier: Intended Audience :: Developers
Classifier: License :: OSI Approved :: Apache Software License
Classifier: Programming Language :: Python
Classifier: Programming Language :: Python :: 2.6
Classifier: Programming Language :: Python :: 2.7
Classifier: Programming Language :: Python :: 3.2
Classifier: Programming Language :: Python :: 3.3
Classifier: Topic :: Software Development
Classifier: Topic :: Software Development :: Libraries
Classifier: Topic :: Software Development :: Libraries :: Python Modules
